LICENSE
README.md
setup.py
TypeHub.egg-info/PKG-INFO
TypeHub.egg-info/SOURCES.txt
TypeHub.egg-info/dependency_links.txt
TypeHub.egg-info/requires.txt
TypeHub.egg-info/top_level.txt
typehub/__init__.py
typehub/color_structures.py
typehub/common.py
typehub/geometry_structures.py
typehub/version.py